{"hypothesis_id":23224,"drug":"Dimethyl fumarate","outcome":"brain malignancy","total_trials":1,"fetched_at":"2026-05-12T21:25:47+00:00","search_url":"https://clinicaltrials.gov/search?intr=Dimethyl+fumarate&cond=brain+malignancy","trials":[{"nct_id":"NCT02337426","title":"Dimethyl Fumarate, Temozolomide, and Radiation Therapy in Treating Patients With Newly Diagnosed Glioblastoma Multiforme","phases":["PHASE1"],"overall_status":"COMPLETED","study_type":"INTERVENTIONAL","start_date":"2015-02-13","completion_date":"2017-11-09","last_update_date":"2019-06-28","conditions":["Adult Brain Glioblastoma","Adult Giant Cell Glioblastoma","Adult Gliosarcoma"],"interventions":[{"name":"Dimethyl Fumarate","type":"DRUG","other_names":["Fumaric Acid, Dimethyl Ester"]},{"name":"Temozolomide","type":"DRUG","other_names":["TMZ"]},{"name":"Radiation Therapy","type":"RADIATION","other_names":["Cancer Radiotherapy","Irradiate","Irradiated","Irradiation","RT"]}],"sponsor":"Virginia Commonwealth University"}]}