{"hypothesis_id":25874,"drug":"resveratrol","outcome":"diabetic nephropathy","total_trials":1,"fetched_at":"2026-05-12T21:25:47+00:00","search_url":"https://clinicaltrials.gov/search?intr=resveratrol&cond=diabetic+nephropathy","trials":[{"nct_id":"NCT02704494","title":"Resveratrol's Effects in Diabetic Nephropathy","phases":["EARLY_PHASE1"],"overall_status":"COMPLETED","study_type":"INTERVENTIONAL","start_date":"2016-03-01","completion_date":"2017-02-01","last_update_date":"2017-10-05","conditions":["Diabetic Nephropathy"],"interventions":[{"name":"Resveratrol","type":"DRUG","other_names":[]},{"name":"Placebo","type":"DRUG","other_names":[]},{"name":"Losartan","type":"DRUG","other_names":[]}],"sponsor":"Shiraz University of Medical Sciences"}]}