{"hypothesis_id":32918,"drug":"5-ASA","outcome":"epilepsy","total_trials":1,"fetched_at":"2026-05-12T21:25:47+00:00","search_url":"https://clinicaltrials.gov/search?intr=5-ASA&cond=epilepsy","trials":[{"nct_id":"NCT07421661","title":"Effect of Epilepsy and Antiepileptic Drug Therapy on Gastric Motility and Emptying With Point-Of-Care Gastric Ultrasound","phases":[],"overall_status":"NOT_YET_RECRUITING","study_type":"OBSERVATIONAL","start_date":"2026-04-01","completion_date":"2028-04-30","last_update_date":"2026-02-19","conditions":["Epilepsy"],"interventions":[{"name":"Gastric Ultrasound","type":"PROCEDURE","other_names":[]}],"sponsor":"London Health Sciences Centre Research Institute OR Lawson Research Institute of St. Joseph's"}]}