{"hypothesis_id":32912,"drug":"Melatonin","outcome":"epilepsy","total_trials":10,"fetched_at":"2026-05-12T21:25:47+00:00","search_url":"https://clinicaltrials.gov/search?intr=Melatonin&cond=epilepsy","trials":[{"nct_id":"NCT07221968","title":"Melatonin for the Treatment of DEE-SWAS","phases":["PHASE2"],"overall_status":"NOT_YET_RECRUITING","study_type":"INTERVENTIONAL","start_date":"2026-07-01","completion_date":"2028-12-30","last_update_date":"2025-10-30","conditions":["CSWS","Developmental and/or Epileptic Encephalopathies","Electrical Status Epilepticus in Sleep"],"interventions":[{"name":"Melatonin","type":"DRUG","other_names":[]}],"sponsor":"Hugo W. Moser Research Institute at Kennedy Krieger, Inc."},{"nct_id":"NCT05439876","title":"Getting SMART for Pediatric Epilepsy","phases":["PHASE2","PHASE3"],"overall_status":"COMPLETED","study_type":"INTERVENTIONAL","start_date":"2022-07-18","completion_date":"2025-01-03","last_update_date":"2025-08-29","conditions":["Epilepsy in Children"],"interventions":[{"name":"Melatonin","type":"DRUG","other_names":["Melatonin supplement"]},{"name":"Placebo","type":"DRUG","other_names":["Starch pill"]}],"sponsor":"National Taiwan University Hospital"},{"nct_id":"NCT04665453","title":"Dexmedetomidine and Melatonin for Sleep Induction for EEG in Children","phases":["NA"],"overall_status":"COMPLETED","study_type":"INTERVENTIONAL","start_date":"2020-09-01","completion_date":"2022-10-01","last_update_date":"2022-11-02","conditions":["Electroencephalography","Child","Dexmedetomidine","Melatonin","Sleep","Epilepsy"],"interventions":[{"name":"Electroencephalography","type":"DIAGNOSTIC_TEST","other_names":["EEG"]},{"name":"Monitoring of vital functions","type":"DIAGNOSTIC_TEST","other_names":[]},{"name":"Melatonin 0,1mg/kg oral syrup","type":"DRUG","other_names":[]},{"name":"Dexmedetomidine 3 mcg/kg sublingually","type":"DRUG","other_names":[]},{"name":"Dexmedetomidine 3 mcg/kg intranasally","type":"DRUG","other_names":[]}],"sponsor":"University Medical Centre Ljubljana"},{"nct_id":"NCT00965575","title":"Pilot Study of Melatonin and Epilepsy","phases":["PHASE2"],"overall_status":"COMPLETED","study_type":"INTERVENTIONAL","start_date":"2011-06-01","completion_date":"2014-08-01","last_update_date":"2020-10-01","conditions":["Epilepsy"],"interventions":[{"name":"Melatonin","type":"DRUG","other_names":["natural supplement"]},{"name":"Placebos","type":"DRUG","other_names":["Placebo"]}],"sponsor":"Children's Hospital Medical Center, Cincinnati"},{"nct_id":"NCT03590197","title":"Effect of Melatonin on Seizure Outcome, Neuronal Damage and Quality of Life in Patients With Generalized Epilepsy","phases":["PHASE4"],"overall_status":"COMPLETED","study_type":"INTERVENTIONAL","start_date":"2018-08-06","completion_date":"2020-04-12","last_update_date":"2020-09-03","conditions":["Generalized Epilepsy"],"interventions":[{"name":"Melatonin 3 mg","type":"DRUG","other_names":[]},{"name":"Placebo","type":"OTHER","other_names":[]}],"sponsor":"All India Institute of Medical Sciences, Bhubaneswar"},{"nct_id":"NCT02195661","title":"The Role of Melatonin in the Effective Attainment of Sleep Electroencephalograms (EEG) in Children","phases":["PHASE3"],"overall_status":"COMPLETED","study_type":"INTERVENTIONAL","start_date":"2014-04-01","completion_date":"2017-10-01","last_update_date":"2017-11-30","conditions":["Epilepsy","Electroencephalogram","Children","Sedation"],"interventions":[{"name":"Melatonin","type":"DIETARY_SUPPLEMENT","other_names":[]},{"name":"Chloral Hydrate","type":"DRUG","other_names":[]}],"sponsor":"University of Cape Town"},{"nct_id":"NCT01161108","title":"Trial of Melatonin to Improve Sleep in Children With Epilepsy and Neurodevelopmental Disabilities","phases":["PHASE3"],"overall_status":"COMPLETED","study_type":"INTERVENTIONAL","start_date":"2010-07-01","completion_date":"2012-06-01","last_update_date":"2014-12-02","conditions":["Epilepsy","Insomnia","Developmental Disability"],"interventions":[{"name":"Fast Release Melatonin (FR MLT)","type":"DRUG","other_names":["Sleep Tight TM by Nature's Harmony® Melatonin"]},{"name":"Fast Release Placebo","type":"DRUG","other_names":[]},{"name":"Timed Release Melatonin (TR MLT)","type":"DRUG","other_names":["Melatonin Timed Release by General Nutrition Canada"]},{"name":"Timed Release Placebo","type":"DRUG","other_names":[]}],"sponsor":"The Hospital for Sick Children"},{"nct_id":"NCT01370486","title":"Melatonin Versus Placebo in the Lennox-Gastaut Syndrome: Neurophysiological and Neuropsychological Effects","phases":["PHASE4"],"overall_status":"WITHDRAWN","study_type":"INTERVENTIONAL","start_date":"2011-08-01","completion_date":"2012-01-01","last_update_date":"2022-07-14","conditions":["Lennox-Gastaut Syndrome"],"interventions":[{"name":"melatonin","type":"DRUG","other_names":["brand name: circadin"]},{"name":"placebo","type":"DRUG","other_names":[]}],"sponsor":"Institution de Lavigny"},{"nct_id":"NCT05654415","title":"Melatonin vs Sleep Deprivation for Nap EEG","phases":["NA"],"overall_status":"UNKNOWN","study_type":"INTERVENTIONAL","start_date":"2021-09-01","completion_date":"2022-12-31","last_update_date":"2022-12-16","conditions":["Epilepsy"],"interventions":[{"name":"Melatonin","type":"OTHER","other_names":[]},{"name":"Deprivation","type":"OTHER","other_names":[]}],"sponsor":"IRCCS National Neurological Institute \"C. Mondino\" Foundation"},{"nct_id":"NCT05256173","title":"Clinical Study on the Effect of Improving Sleep Quality on Cognitive Function in Patients With Epilepsy","phases":["NA"],"overall_status":"UNKNOWN","study_type":"INTERVENTIONAL","start_date":"2022-02-01","completion_date":"2022-11-01","last_update_date":"2022-02-25","conditions":["Epilepsy，Cognition"],"interventions":[{"name":"Melatonin Tablets","type":"OTHER","other_names":[]},{"name":"Lactasin Tablets","type":"OTHER","other_names":[]},{"name":"transcutaneous vagus nerve stimulation","type":"DEVICE","other_names":[]},{"name":"sham transcutaneous vagus nerve stimulation","type":"DEVICE","other_names":[]}],"sponsor":"Xijing Hospital"}]}