{"hypothesis_id":35474,"drug":"DMF","outcome":"rheumatoid arthritis","total_trials":1,"fetched_at":"2026-05-12T21:25:47+00:00","search_url":"https://clinicaltrials.gov/search?intr=DMF&cond=rheumatoid+arthritis","trials":[{"nct_id":"NCT00810836","title":"Efficacy and Safety Study of BG00012 With Methotrexate in Patients With Active Rheumatoid Arthritis","phases":["PHASE2"],"overall_status":"COMPLETED","study_type":"INTERVENTIONAL","start_date":"2008-12-01","completion_date":"2010-03-01","last_update_date":"2013-09-16","conditions":["Rheumatoid Arthritis"],"interventions":[{"name":"BG00012","type":"DRUG","other_names":[]},{"name":"BG00012","type":"DRUG","other_names":[]},{"name":"placebo","type":"DRUG","other_names":[]}],"sponsor":"Biogen"}]}