{
  "hypothesis_id": 1575,
  "drug": "type-II kinase inhibitors",
  "mediator": "EGFR",
  "outcome": "pancreatic ductal adenocarcinoma",
  "outcome_domain": "pancreatic_cancer",
  "generated_at": "2026-05-12T22:27:22+00:00",
  "method": "embedding_cosine_with_structural_bonus_v1",
  "similar": [
    {
      "id": 1628,
      "drug": "mAb806",
      "mediator": "EGFR",
      "outcome": "pancreatic ductal adenocarcinoma",
      "outcome_domain": "pancreatic_cancer",
      "score": 0.20794415416798356,
      "similarity_score": 0.88,
      "cosine_component": 1.0,
      "structural_component": 0.7,
      "jaccard_component": 1.0,
      "quality_tier": "mid",
      "match_type": "alternative_treatment",
      "is_case_study": false
    },
    {
      "id": 1639,
      "drug": "STA",
      "mediator": "EGFR",
      "outcome": "pancreatic ductal adenocarcinoma",
      "outcome_domain": "pancreatic_cancer",
      "score": 0.20794415416798356,
      "similarity_score": 0.8244,
      "cosine_component": 0.9687,
      "structural_component": 0.7,
      "jaccard_component": 0.6,
      "quality_tier": "mid",
      "match_type": "alternative_treatment",
      "is_case_study": false
    },
    {
      "id": 1583,
      "drug": "anti-EGFR-coated Raman tags",
      "mediator": "EGFR",
      "outcome": "pancreatic ductal adenocarcinoma",
      "outcome_domain": "pancreatic_cancer",
      "score": 0.20794415416798356,
      "similarity_score": 0.8237,
      "cosine_component": 0.9674,
      "structural_component": 0.7,
      "jaccard_component": 0.6,
      "quality_tier": "mid",
      "match_type": "alternative_treatment",
      "is_case_study": false
    },
    {
      "id": 1618,
      "drug": "dual inhibitors",
      "mediator": "EGFR",
      "outcome": "pancreatic ductal adenocarcinoma",
      "outcome_domain": "pancreatic_cancer",
      "score": 0.20794415416798356,
      "similarity_score": 0.8227,
      "cosine_component": 0.9654,
      "structural_component": 0.7,
      "jaccard_component": 0.6,
      "quality_tier": "mid",
      "match_type": "alternative_treatment",
      "is_case_study": false
    },
    {
      "id": 1616,
      "drug": "Isochaihulactone",
      "mediator": "EGFR",
      "outcome": "pancreatic ductal adenocarcinoma",
      "outcome_domain": "pancreatic_cancer",
      "score": 0.20794415416798356,
      "similarity_score": 0.822,
      "cosine_component": 0.9639,
      "structural_component": 0.7,
      "jaccard_component": 0.6,
      "quality_tier": "mid",
      "match_type": "alternative_treatment",
      "is_case_study": false
    },
    {
      "id": 1608,
      "drug": "carborane-containing bioisostere of erlotinib",
      "mediator": "EGFR",
      "outcome": "pancreatic ductal adenocarcinoma",
      "outcome_domain": "pancreatic_cancer",
      "score": 0.20794415416798356,
      "similarity_score": 0.8219,
      "cosine_component": 0.9638,
      "structural_component": 0.7,
      "jaccard_component": 0.6,
      "quality_tier": "mid",
      "match_type": "alternative_treatment",
      "is_case_study": false
    },
    {
      "id": 1636,
      "drug": "LASSBio-1971",
      "mediator": "EGFR",
      "outcome": "pancreatic ductal adenocarcinoma",
      "outcome_domain": "pancreatic_cancer",
      "score": 0.20794415416798356,
      "similarity_score": 0.8219,
      "cosine_component": 0.9637,
      "structural_component": 0.7,
      "jaccard_component": 0.6,
      "quality_tier": "mid",
      "match_type": "alternative_treatment",
      "is_case_study": false
    },
    {
      "id": 1572,
      "drug": "dacomitinib",
      "mediator": "EGFR",
      "outcome": "pancreatic ductal adenocarcinoma",
      "outcome_domain": "pancreatic_cancer",
      "score": 0.20794415416798356,
      "similarity_score": 0.8216,
      "cosine_component": 0.9632,
      "structural_component": 0.7,
      "jaccard_component": 0.6,
      "quality_tier": "mid",
      "match_type": "alternative_treatment",
      "is_case_study": false
    }
  ]
}