{
  "hypothesis_id": 2577,
  "drug": "valproic acid",
  "mediator": "GLI1",
  "outcome": "liver cancer stem cell function",
  "outcome_domain": "pancreatic_cancer",
  "generated_at": "2026-05-12T22:27:22+00:00",
  "method": "embedding_cosine_with_structural_bonus_v1",
  "similar": [
    {
      "id": 326,
      "drug": "valproic acid",
      "mediator": "GLI1",
      "outcome": "venous thromboembolism",
      "outcome_domain": "glioblastoma",
      "score": 0.13862943611198905,
      "similarity_score": 0.8072,
      "cosine_component": 0.8678,
      "structural_component": 0.85,
      "jaccard_component": 0.3333,
      "quality_tier": "mid",
      "match_type": "same_mechanism_new_indication",
      "is_case_study": false
    },
    {
      "id": 2502,
      "drug": "valproic acid",
      "mediator": "GLI1",
      "outcome": "nerve plexus density",
      "outcome_domain": "pancreatic_cancer",
      "score": 0.13862943611198905,
      "similarity_score": 0.8049,
      "cosine_component": 0.8631,
      "structural_component": 0.85,
      "jaccard_component": 0.3333,
      "quality_tier": "mid",
      "match_type": "same_mechanism_new_indication",
      "is_case_study": false
    },
    {
      "id": 346,
      "drug": "valproic acid",
      "mediator": "NRF2",
      "outcome": "patient survival",
      "outcome_domain": "glioblastoma",
      "score": 0.1791759469228055,
      "similarity_score": 0.7688,
      "cosine_component": 0.7376,
      "structural_component": 1.0,
      "jaccard_component": 0.0,
      "quality_tier": "mid",
      "match_type": "cross_indication",
      "is_case_study": false
    },
    {
      "id": 37097,
      "drug": "valproic acid",
      "mediator": "ERBB3",
      "outcome": "endometriosis",
      "outcome_domain": "multiple_sclerosis",
      "score": 0.13862943611198905,
      "similarity_score": 0.7681,
      "cosine_component": 0.7362,
      "structural_component": 1.0,
      "jaccard_component": 0.0,
      "quality_tier": "mid",
      "match_type": "cross_indication",
      "is_case_study": false
    },
    {
      "id": 37098,
      "drug": "valproic acid",
      "mediator": "ERBB3",
      "outcome": "multiple sclerosis",
      "outcome_domain": "multiple_sclerosis",
      "score": 0.13862943611198905,
      "similarity_score": 0.7681,
      "cosine_component": 0.7362,
      "structural_component": 1.0,
      "jaccard_component": 0.0,
      "quality_tier": "mid",
      "match_type": "cross_indication",
      "is_case_study": false
    },
    {
      "id": 7053,
      "drug": "valproic acid",
      "mediator": "HDAC3",
      "outcome": "clinical stage",
      "outcome_domain": "pancreatic_cancer",
      "score": 0.20794415416798356,
      "similarity_score": 0.7662,
      "cosine_component": 0.7324,
      "structural_component": 1.0,
      "jaccard_component": 0.0,
      "quality_tier": "high",
      "match_type": "cross_indication",
      "is_case_study": false
    },
    {
      "id": 7054,
      "drug": "valproic acid",
      "mediator": "HDAC3",
      "outcome": "lymph node metastasis",
      "outcome_domain": "pancreatic_cancer",
      "score": 0.20794415416798356,
      "similarity_score": 0.7662,
      "cosine_component": 0.7324,
      "structural_component": 1.0,
      "jaccard_component": 0.0,
      "quality_tier": "high",
      "match_type": "cross_indication",
      "is_case_study": false
    },
    {
      "id": 266,
      "drug": "valproic acid",
      "mediator": "TGFβ signaling",
      "outcome": "recurrence",
      "outcome_domain": "glioblastoma",
      "score": 0.13862943611198905,
      "similarity_score": 0.7656,
      "cosine_component": 0.7312,
      "structural_component": 1.0,
      "jaccard_component": 0.0,
      "quality_tier": "mid",
      "match_type": "cross_indication",
      "is_case_study": false
    }
  ]
}