{
  "hypothesis_id": 28274,
  "drug": "fluoxetine",
  "mediator": "TLR7",
  "outcome": "colitis",
  "outcome_domain": "inflammatory_bowel_disease",
  "generated_at": "2026-05-12T22:27:22+00:00",
  "method": "embedding_cosine_with_structural_bonus_v1",
  "similar": [
    {
      "id": 28283,
      "drug": "fluoxetine",
      "mediator": "TLR7",
      "outcome": "intestinal inflammation",
      "outcome_domain": "inflammatory_bowel_disease",
      "score": 0.13862943611198905,
      "similarity_score": 0.94,
      "cosine_component": 1.0,
      "structural_component": 0.85,
      "jaccard_component": 1.0,
      "quality_tier": "mid",
      "match_type": "same_mechanism_new_indication",
      "is_case_study": false
    },
    {
      "id": 28755,
      "drug": "fluoxetine",
      "mediator": "TLR7",
      "outcome": "type 1 diabetes",
      "outcome_domain": "type_2_diabetes",
      "score": 0.13862943611198905,
      "similarity_score": 0.8188,
      "cosine_component": 0.8908,
      "structural_component": 0.85,
      "jaccard_component": 0.3333,
      "quality_tier": "mid",
      "match_type": "same_mechanism_new_indication",
      "is_case_study": false
    },
    {
      "id": 5451,
      "drug": "fluoxetine",
      "mediator": "TLR7",
      "outcome": "cell proliferation",
      "outcome_domain": "pancreatic_cancer",
      "score": 0.13862943611198905,
      "similarity_score": 0.8079,
      "cosine_component": 0.8692,
      "structural_component": 0.85,
      "jaccard_component": 0.3333,
      "quality_tier": "mid",
      "match_type": "same_mechanism_new_indication",
      "is_case_study": false
    },
    {
      "id": 5465,
      "drug": "fluoxetine",
      "mediator": "TLR7",
      "outcome": "chemosensitivity",
      "outcome_domain": "pancreatic_cancer",
      "score": 0.13862943611198905,
      "similarity_score": 0.8079,
      "cosine_component": 0.8692,
      "structural_component": 0.85,
      "jaccard_component": 0.3333,
      "quality_tier": "mid",
      "match_type": "same_mechanism_new_indication",
      "is_case_study": false
    },
    {
      "id": 5474,
      "drug": "fluoxetine",
      "mediator": "TLR7",
      "outcome": "good prognosis",
      "outcome_domain": "pancreatic_cancer",
      "score": 0.13862943611198905,
      "similarity_score": 0.7985,
      "cosine_component": 0.8504,
      "structural_component": 0.85,
      "jaccard_component": 0.3333,
      "quality_tier": "mid",
      "match_type": "same_mechanism_new_indication",
      "is_case_study": false
    },
    {
      "id": 31377,
      "drug": "linalool",
      "mediator": "PD-L1",
      "outcome": "colitis",
      "outcome_domain": "inflammatory_bowel_disease",
      "score": 0.1791759469228055,
      "similarity_score": 0.6407,
      "cosine_component": 0.7214,
      "structural_component": 0.7,
      "jaccard_component": 0.0,
      "quality_tier": "mid",
      "match_type": "alternative_treatment",
      "is_case_study": false
    },
    {
      "id": 36898,
      "drug": "niclosamide",
      "mediator": "PD-L1",
      "outcome": "colitis",
      "outcome_domain": "inflammatory_bowel_disease",
      "score": 0.1791759469228055,
      "similarity_score": 0.634,
      "cosine_component": 0.7081,
      "structural_component": 0.7,
      "jaccard_component": 0.0,
      "quality_tier": "mid",
      "match_type": "alternative_treatment",
      "is_case_study": false
    },
    {
      "id": 31335,
      "drug": "temozolomide",
      "mediator": "PD-L1",
      "outcome": "colitis",
      "outcome_domain": "inflammatory_bowel_disease",
      "score": 0.21972245773362195,
      "similarity_score": 0.6312,
      "cosine_component": 0.7024,
      "structural_component": 0.7,
      "jaccard_component": 0.0,
      "quality_tier": "mid",
      "match_type": "alternative_treatment",
      "is_case_study": false
    }
  ]
}