{
  "hypothesis_id": 4212,
  "drug": "curcumin",
  "mediator": "BDNF",
  "outcome": "depressive disorder",
  "outcome_domain": "depression",
  "generated_at": "2026-05-12T22:27:22+00:00",
  "method": "embedding_cosine_with_structural_bonus_v1",
  "similar": [
    {
      "id": 4238,
      "drug": "curcumin",
      "mediator": "BDNF",
      "outcome": "major depression",
      "outcome_domain": "depression",
      "score": 0.13862943611198905,
      "similarity_score": 0.8155,
      "cosine_component": 0.8844,
      "structural_component": 0.85,
      "jaccard_component": 0.3333,
      "quality_tier": "mid",
      "match_type": "same_mechanism_new_indication",
      "is_case_study": false
    },
    {
      "id": 20859,
      "drug": "curcumin",
      "mediator": "BDNF",
      "outcome": "depressive symptoms",
      "outcome_domain": "depression",
      "score": 0.13862943611198905,
      "similarity_score": 0.8126,
      "cosine_component": 0.8785,
      "structural_component": 0.85,
      "jaccard_component": 0.3333,
      "quality_tier": "mid",
      "match_type": "same_mechanism_new_indication",
      "is_case_study": false
    },
    {
      "id": 4303,
      "drug": "curcumin",
      "mediator": "BDNF",
      "outcome": "MDD",
      "outcome_domain": "depression",
      "score": 0.13862943611198905,
      "similarity_score": 0.8116,
      "cosine_component": 0.8766,
      "structural_component": 0.85,
      "jaccard_component": 0.3333,
      "quality_tier": "mid",
      "match_type": "same_mechanism_new_indication",
      "is_case_study": false
    },
    {
      "id": 14779,
      "drug": "curcumin",
      "mediator": "BDNF",
      "outcome": "visuospatial ability",
      "outcome_domain": "depression",
      "score": 0.13862943611198905,
      "similarity_score": 0.8109,
      "cosine_component": 0.8751,
      "structural_component": 0.85,
      "jaccard_component": 0.3333,
      "quality_tier": "mid",
      "match_type": "same_mechanism_new_indication",
      "is_case_study": false
    },
    {
      "id": 4346,
      "drug": "curcumin",
      "mediator": "BDNF",
      "outcome": "language function",
      "outcome_domain": "depression",
      "score": 0.13862943611198905,
      "similarity_score": 0.8109,
      "cosine_component": 0.8751,
      "structural_component": 0.85,
      "jaccard_component": 0.3333,
      "quality_tier": "mid",
      "match_type": "same_mechanism_new_indication",
      "is_case_study": false
    },
    {
      "id": 4213,
      "drug": "curcumin",
      "mediator": "BDNF",
      "outcome": "suicide risk",
      "outcome_domain": "depression",
      "score": 0.13862943611198905,
      "similarity_score": 0.8103,
      "cosine_component": 0.874,
      "structural_component": 0.85,
      "jaccard_component": 0.3333,
      "quality_tier": "mid",
      "match_type": "same_mechanism_new_indication",
      "is_case_study": false
    },
    {
      "id": 4319,
      "drug": "curcumin",
      "mediator": "BDNF",
      "outcome": "improvement in depressive symptoms",
      "outcome_domain": "depression",
      "score": 0.13862943611198905,
      "similarity_score": 0.8084,
      "cosine_component": 0.8702,
      "structural_component": 0.85,
      "jaccard_component": 0.3333,
      "quality_tier": "mid",
      "match_type": "same_mechanism_new_indication",
      "is_case_study": false
    },
    {
      "id": 4334,
      "drug": "curcumin",
      "mediator": "BDNF",
      "outcome": "anhedonia",
      "outcome_domain": "depression",
      "score": 0.13862943611198905,
      "similarity_score": 0.8055,
      "cosine_component": 0.8644,
      "structural_component": 0.85,
      "jaccard_component": 0.3333,
      "quality_tier": "mid",
      "match_type": "same_mechanism_new_indication",
      "is_case_study": false
    }
  ]
}