{
  "hypothesis_id": 5317,
  "drug": "JNJ-54175446",
  "mediator": "P2X7R",
  "outcome": "seizure severity",
  "outcome_domain": "epilepsy",
  "generated_at": "2026-05-12T22:27:22+00:00",
  "method": "embedding_cosine_with_structural_bonus_v1",
  "similar": [
    {
      "id": 5318,
      "drug": "JNJ-54175446",
      "mediator": "P2X7R",
      "outcome": "temporal lobe epilepsy",
      "outcome_domain": "epilepsy",
      "score": 0.20794415416798356,
      "similarity_score": 0.8556,
      "cosine_component": 0.9513,
      "structural_component": 0.85,
      "jaccard_component": 0.4,
      "quality_tier": "mid",
      "match_type": "same_mechanism_new_indication",
      "is_case_study": false
    },
    {
      "id": 562,
      "drug": "AZ10606120",
      "mediator": "P2X7R",
      "outcome": "seizure severity",
      "outcome_domain": "epilepsy",
      "score": 0.20794415416798356,
      "similarity_score": 0.8014,
      "cosine_component": 0.9428,
      "structural_component": 0.7,
      "jaccard_component": 0.5,
      "quality_tier": "mid",
      "match_type": "alternative_treatment",
      "is_case_study": false
    },
    {
      "id": 563,
      "drug": "AZ10606120",
      "mediator": "P2X7R",
      "outcome": "temporal lobe epilepsy",
      "outcome_domain": "epilepsy",
      "score": 0.20794415416798356,
      "similarity_score": 0.7064,
      "cosine_component": 0.8996,
      "structural_component": 0.6,
      "jaccard_component": 0.1667,
      "quality_tier": "mid",
      "match_type": "mechanism_shared",
      "is_case_study": false
    },
    {
      "id": 3592,
      "drug": "TFSeB",
      "mediator": "BDNF",
      "outcome": "epilepsy",
      "outcome_domain": "epilepsy",
      "score": 0.23025850929940456,
      "similarity_score": 0.3849,
      "cosine_component": 0.7699,
      "structural_component": 0.0,
      "jaccard_component": 0.0,
      "quality_tier": "mid",
      "match_type": "topical",
      "is_case_study": false
    },
    {
      "id": 7648,
      "drug": "Palmitoylethanolamide",
      "mediator": "BDNF",
      "outcome": "epilepsy",
      "outcome_domain": "epilepsy",
      "score": 0.23025850929940456,
      "similarity_score": 0.3813,
      "cosine_component": 0.7625,
      "structural_component": 0.0,
      "jaccard_component": 0.0,
      "quality_tier": "mid",
      "match_type": "topical",
      "is_case_study": false
    },
    {
      "id": 10444,
      "drug": "Calycosin",
      "mediator": "BDNF",
      "outcome": "epilepsy",
      "outcome_domain": "epilepsy",
      "score": 0.23025850929940456,
      "similarity_score": 0.3798,
      "cosine_component": 0.7596,
      "structural_component": 0.0,
      "jaccard_component": 0.0,
      "quality_tier": "mid",
      "match_type": "topical",
      "is_case_study": false
    },
    {
      "id": 3609,
      "drug": "GQ1b",
      "mediator": "BDNF",
      "outcome": "epilepsy",
      "outcome_domain": "epilepsy",
      "score": 0.23025850929940456,
      "similarity_score": 0.3796,
      "cosine_component": 0.7592,
      "structural_component": 0.0,
      "jaccard_component": 0.0,
      "quality_tier": "mid",
      "match_type": "topical",
      "is_case_study": false
    },
    {
      "id": 3644,
      "drug": "GJD",
      "mediator": "BDNF",
      "outcome": "epilepsy",
      "outcome_domain": "epilepsy",
      "score": 0.23025850929940456,
      "similarity_score": 0.3794,
      "cosine_component": 0.7588,
      "structural_component": 0.0,
      "jaccard_component": 0.0,
      "quality_tier": "mid",
      "match_type": "topical",
      "is_case_study": false
    }
  ]
}