{
  "hypothesis_id": 7257,
  "drug": "SVHRP",
  "mediator": "NPY",
  "outcome": "appetite changes",
  "outcome_domain": "depression",
  "generated_at": "2026-05-12T22:27:22+00:00",
  "method": "embedding_cosine_with_structural_bonus_v1",
  "similar": [
    {
      "id": 7263,
      "drug": "SVHRP",
      "mediator": "BDNF",
      "outcome": "schizophrenia",
      "outcome_domain": "depression",
      "score": 0.20794415416798356,
      "similarity_score": 0.8502,
      "cosine_component": 0.8503,
      "structural_component": 1.0,
      "jaccard_component": 0.25,
      "quality_tier": "mid",
      "match_type": "cross_indication",
      "is_case_study": false
    },
    {
      "id": 3616,
      "drug": "Sinapic acid",
      "mediator": "BDNF",
      "outcome": "epilepsy",
      "outcome_domain": "epilepsy",
      "score": 0.23025850929940456,
      "similarity_score": 0.3925,
      "cosine_component": 0.785,
      "structural_component": 0.0,
      "jaccard_component": 0.0,
      "quality_tier": "mid",
      "match_type": "topical",
      "is_case_study": false
    },
    {
      "id": 7264,
      "drug": "gastrodin",
      "mediator": "BDNF",
      "outcome": "schizophrenia",
      "outcome_domain": "depression",
      "score": 0.20794415416798356,
      "similarity_score": 0.3904,
      "cosine_component": 0.7808,
      "structural_component": 0.0,
      "jaccard_component": 0.0,
      "quality_tier": "mid",
      "match_type": "topical",
      "is_case_study": false
    },
    {
      "id": 10444,
      "drug": "Calycosin",
      "mediator": "BDNF",
      "outcome": "epilepsy",
      "outcome_domain": "epilepsy",
      "score": 0.23025850929940456,
      "similarity_score": 0.3902,
      "cosine_component": 0.7803,
      "structural_component": 0.0,
      "jaccard_component": 0.0,
      "quality_tier": "mid",
      "match_type": "topical",
      "is_case_study": false
    },
    {
      "id": 7648,
      "drug": "Palmitoylethanolamide",
      "mediator": "BDNF",
      "outcome": "epilepsy",
      "outcome_domain": "epilepsy",
      "score": 0.23025850929940456,
      "similarity_score": 0.3896,
      "cosine_component": 0.7792,
      "structural_component": 0.0,
      "jaccard_component": 0.0,
      "quality_tier": "mid",
      "match_type": "topical",
      "is_case_study": false
    },
    {
      "id": 7338,
      "drug": "Baicalin",
      "mediator": "BDNF",
      "outcome": "major depression",
      "outcome_domain": "depression",
      "score": 0.13862943611198905,
      "similarity_score": 0.3889,
      "cosine_component": 0.7777,
      "structural_component": 0.0,
      "jaccard_component": 0.0,
      "quality_tier": "mid",
      "match_type": "topical",
      "is_case_study": false
    },
    {
      "id": 23218,
      "drug": "mitoxantrone",
      "mediator": "BDNF",
      "outcome": "epilepsy",
      "outcome_domain": "epilepsy",
      "score": 0.23025850929940456,
      "similarity_score": 0.3883,
      "cosine_component": 0.7766,
      "structural_component": 0.0,
      "jaccard_component": 0.0,
      "quality_tier": "mid",
      "match_type": "topical",
      "is_case_study": false
    },
    {
      "id": 10443,
      "drug": "AIGG",
      "mediator": "BDNF",
      "outcome": "epilepsy",
      "outcome_domain": "epilepsy",
      "score": 0.23025850929940456,
      "similarity_score": 0.3875,
      "cosine_component": 0.7751,
      "structural_component": 0.0,
      "jaccard_component": 0.0,
      "quality_tier": "mid",
      "match_type": "topical",
      "is_case_study": false
    }
  ]
}