{
  "hypothesis_id": 8048,
  "drug": "Riluzole",
  "mediator": "CK1δ",
  "outcome": "bladder cancer",
  "outcome_domain": "pancreatic_cancer",
  "generated_at": "2026-05-12T22:27:22+00:00",
  "method": "embedding_cosine_with_structural_bonus_v1",
  "similar": [
    {
      "id": 8055,
      "drug": "Riluzole",
      "mediator": "CK1δ",
      "outcome": "pancreatic cancer",
      "outcome_domain": "pancreatic_cancer",
      "score": 0.1791759469228055,
      "similarity_score": 0.94,
      "cosine_component": 1.0,
      "structural_component": 0.85,
      "jaccard_component": 1.0,
      "quality_tier": "mid",
      "match_type": "same_mechanism_new_indication",
      "is_case_study": false
    },
    {
      "id": 3078,
      "drug": "Riluzole",
      "mediator": "CK1δ",
      "outcome": "tau aggregation",
      "outcome_domain": "alzheimer",
      "score": 0.1791759469228055,
      "similarity_score": 0.8565,
      "cosine_component": 0.9331,
      "structural_component": 0.85,
      "jaccard_component": 0.5,
      "quality_tier": "mid",
      "match_type": "same_mechanism_new_indication",
      "is_case_study": false
    },
    {
      "id": 37769,
      "drug": "riluzole",
      "mediator": "TDP-43",
      "outcome": "Alzheimer's disease",
      "outcome_domain": "als",
      "score": 0.1791759469228055,
      "similarity_score": 0.795,
      "cosine_component": 0.79,
      "structural_component": 1.0,
      "jaccard_component": 0.0,
      "quality_tier": "mid",
      "match_type": "cross_indication",
      "is_case_study": false
    },
    {
      "id": 37809,
      "drug": "riluzole",
      "mediator": "TDP-43",
      "outcome": "neuronal dysfunction",
      "outcome_domain": "als",
      "score": 0.1791759469228055,
      "similarity_score": 0.7947,
      "cosine_component": 0.7895,
      "structural_component": 1.0,
      "jaccard_component": 0.0,
      "quality_tier": "mid",
      "match_type": "cross_indication",
      "is_case_study": false
    },
    {
      "id": 37692,
      "drug": "riluzole",
      "mediator": "TDP-43",
      "outcome": "FTLD",
      "outcome_domain": "als",
      "score": 0.20794415416798356,
      "similarity_score": 0.7944,
      "cosine_component": 0.7888,
      "structural_component": 1.0,
      "jaccard_component": 0.0,
      "quality_tier": "high",
      "match_type": "cross_indication",
      "is_case_study": false
    },
    {
      "id": 37810,
      "drug": "riluzole",
      "mediator": "TDP-43",
      "outcome": "neurodegenerative diseases",
      "outcome_domain": "als",
      "score": 0.1791759469228055,
      "similarity_score": 0.7923,
      "cosine_component": 0.7845,
      "structural_component": 1.0,
      "jaccard_component": 0.0,
      "quality_tier": "mid",
      "match_type": "cross_indication",
      "is_case_study": false
    },
    {
      "id": 37791,
      "drug": "riluzole",
      "mediator": "TDP-43",
      "outcome": "neurodegeneration",
      "outcome_domain": "als",
      "score": 0.1791759469228055,
      "similarity_score": 0.7917,
      "cosine_component": 0.7833,
      "structural_component": 1.0,
      "jaccard_component": 0.0,
      "quality_tier": "mid",
      "match_type": "cross_indication",
      "is_case_study": false
    },
    {
      "id": 37802,
      "drug": "riluzole",
      "mediator": "TDP-43",
      "outcome": "frontotemporal dementia",
      "outcome_domain": "als",
      "score": 0.1791759469228055,
      "similarity_score": 0.7897,
      "cosine_component": 0.7794,
      "structural_component": 1.0,
      "jaccard_component": 0.0,
      "quality_tier": "mid",
      "match_type": "cross_indication",
      "is_case_study": false
    }
  ]
}